logita/__init__.py
logita/logger.py
logita-1.3.0.dist-info/licenses/LICENSE
tests/__init__.py
tests/test_logger.py
logita-1.3.0.dist-info/METADATA
logita-1.3.0.dist-info/WHEEL
logita-1.3.0.dist-info/top_level.txt
logita-1.3.0.dist-info/RECORD
