Metadata-Version: 2.4
Name: logita
Version: 1.3.0
Summary: A simple and colorful logging utility for console output with support for context manager.
Author: Jose Luis Coyotzi
Author-email: Jose Luis Coyotzi <jlci811122@gmail.com>
License: MIT
Classifier: Programming Language :: Python :: 3
Classifier: Programming Language :: Python :: 3.6
Classifier: Programming Language :: Python :: 3.7
Classifier: Programming Language :: Python :: 3.8
Classifier: Programming Language :: Python :: 3.9
Classifier: Programming Language :: Python :: 3.10
Classifier: Programming Language :: Python :: 3.11
Classifier: Operating System :: OS Independent
Classifier: License :: OSI Approved :: MIT License
Classifier: Intended Audience :: Developers
Classifier: Topic :: Software Development :: Libraries :: Python Modules
Classifier: Typing :: Typed
Requires-Python: >=3.6
License-File: LICENSE
Requires-Dist: colorama>=0.4.6
Dynamic: author
Dynamic: license-file
Dynamic: requires-python
